MANIFEST.in
README.md
requirements.txt
setup.py
pyairmore/__init__.py
pyairmore.egg-info/PKG-INFO
pyairmore.egg-info/SOURCES.txt
pyairmore.egg-info/dependency_links.txt
pyairmore.egg-info/not-zip-safe
pyairmore.egg-info/requires.txt
pyairmore.egg-info/top_level.txt
pyairmore/request/__init__.py
pyairmore/services/__init__.py
pyairmore/services/device.py
pyairmore/services/messaging.py