Metadata-Version: 2.1
Name: pyairmore
Version: 0.2.0a1
Summary: PyAirmore is a communication layer between an Android Airmore server and the client.
Home-page: https://github.com/erayerdin/pyairmore
Author: Eray Erdin
Author-email: eraygezer.94@gmail.com
License: Apache License 2.0
Download-URL: https://github.com/erayerdin/exceptive/archive/master.zip
Keywords: python android airmore pyairmore
Platform: UNKNOWN
Classifier: Development Status :: 2 - Pre-Alpha
Classifier: Intended Audience :: Developers
Classifier: License :: OSI Approved :: Apache Software License
Classifier: Programming Language :: Python :: 3 :: Only
Classifier: Programming Language :: Python :: 3.5
Classifier: Programming Language :: Python :: 3.6
Classifier: Programming Language :: Python :: 3.7
Classifier: Topic :: Software Development
Classifier: Topic :: System :: Networking :: Monitoring
